<model>
	<voxels>
		<voxel a="1.0" b="0.1647" g="0.2157" r="0.4431" x="-11" y="-7" z="4" />
		<voxel a="1.0" b="0.1647" g="0.2157" r="0.4431" x="-10" y="-7" z="4" />
		<voxel a="1.0" b="0.1647" g="0.2157" r="0.4431" x="-9" y="-7" z="4" />
		<voxel a="1.0" b="0.1647" g="0.2157" r="0.4431" x="-8" y="-7" z="4" />
		<voxel a="1.0" b="0.1647" g="0.2157" r="0.4431" x="-7" y="-7" z="4" />
		<voxel a="1.0" b="0.1647" g="0.2157" r="0.4431" x="-6" y="-7" z="4" />
		<voxel a="1.0" b="0.1647" g="0.2157" r="0.4431" x="-5" y="-7" z="4" />
		<voxel a="1.0" b="0.1647" g="0.2157" r="0.4431" x="-4" y="-7" z="4" />
		<voxel a="1.0" b="0.1647" g="0.2157" r="0.4431" x="-11" y="-7" z="3" />
		<voxel a="1.0" b="0.7608" g="0.298" r="0.2078" x="-10" y="-7" z="3" />
		<voxel a="1.0" b="0.498" g="0.498" r="0.498" x="-9" y="-7" z="3" />
		<voxel a="1.0" b="0.498" g="0.498" r="0.498" x="-8" y="-7" z="3" />
		<voxel a="1.0" b="0.498" g="0.498" r="0.498" x="-7" y="-7" z="3" />
		<voxel a="1.0" b="0.498" g="0.498" r="0.498" x="-6" y="-7" z="3" />
		<voxel a="1.0" b="0.7608" g="0.298" r="0.2078" x="-5" y="-7" z="3" />
		<voxel a="1.0" b="0.1647" g="0.2157" r="0.4431" x="-4" y="-7" z="3" />
		<voxel a="1.0" b="0.1647" g="0.2157" r="0.4431" x="-11" y="-7" z="2" />
		<voxel a="1.0" b="0.498" g="0.498" r="0.498" x="-10" y="-7" z="2" />
		<voxel a="1.0" b="0.7608" g="0.298" r="0.2078" x="-9" y="-7" z="2" />
		<voxel a="1.0" b="0.498" g="0.498" r="0.498" x="-8" y="-7" z="2" />
		<voxel a="1.0" b="0.498" g="0.498" r="0.498" x="-7" y="-7" z="2" />
		<voxel a="1.0" b="0.7608" g="0.298" r="0.2078" x="-6" y="-7" z="2" />
		<voxel a="1.0" b="0.498" g="0.498" r="0.498" x="-5" y="-7" z="2" />
		<voxel a="1.0" b="0.1647" g="0.2157" r="0.4431" x="-4" y="-7" z="2" />
		<voxel a="1.0" b="0.1647" g="0.2157" r="0.4431" x="-11" y="-7" z="1" />
		<voxel a="1.0" b="0.498" g="0.498" r="0.498" x="-10" y="-7" z="1" />
		<voxel a="1.0" b="0.498" g="0.498" r="0.498" x="-9" y="-7" z="1" />
		<voxel a="1.0" b="0.7608" g="0.298" r="0.2078" x="-8" y="-7" z="1" />
		<voxel a="1.0" b="0.7608" g="0.298" r="0.2078" x="-7" y="-7" z="1" />
		<voxel a="1.0" b="0.498" g="0.498" r="0.498" x="-6" y="-7" z="1" />
		<voxel a="1.0" b="0.498" g="0.498" r="0.498" x="-5" y="-7" z="1" />
		<voxel a="1.0" b="0.1647" g="0.2157" r="0.4431" x="-4" y="-7" z="1" />
		<voxel a="1.0" b="0.1647" g="0.2157" r="0.4431" x="-11" y="-7" z="0" />
		<voxel a="1.0" b="0.498" g="0.498" r="0.498" x="-10" y="-7" z="0" />
		<voxel a="1.0" b="0.498" g="0.498" r="0.498" x="-9" y="-7" z="0" />
		<voxel a="1.0" b="0.8039" g="0.1686" r="0.749" x="-8" y="-7" z="0" />
		<voxel a="1.0" b="0.8039" g="0.1686" r="0.749" x="-7" y="-7" z="0" />
		<voxel a="1.0" b="0.498" g="0.498" r="0.498" x="-6" y="-7" z="0" />
		<voxel a="1.0" b="0.498" g="0.498" r="0.498" x="-5" y="-7" z="0" />
		<voxel a="1.0" b="0.1647" g="0.2157" r="0.4431" x="-4" y="-7" z="0" />
		<voxel a="1.0" b="0.1647" g="0.2157" r="0.4431" x="-11" y="-7" z="-1" />
		<voxel a="1.0" b="0.498" g="0.498" r="0.498" x="-10" y="-7" z="-1" />
		<voxel a="1.0" b="0.498" g="0.498" r="0.498" x="-9" y="-7" z="-1" />
		<voxel a="1.0" b="0.7608" g="0.298" r="0.2078" x="-8" y="-7" z="-1" />
		<voxel a="1.0" b="0.7608" g="0.298" r="0.2078" x="-7" y="-7" z="-1" />
		<voxel a="1.0" b="0.498" g="0.498" r="0.498" x="-6" y="-7" z="-1" />
		<voxel a="1.0" b="0.498" g="0.498" r="0.498" x="-5" y="-7" z="-1" />
		<voxel a="1.0" b="0.1647" g="0.2157" r="0.4431" x="-4" y="-7" z="-1" />
		<voxel a="1.0" b="0.1647" g="0.2157" r="0.4431" x="-11" y="-7" z="-2" />
		<voxel a="1.0" b="0.498" g="0.498" r="0.498" x="-10" y="-7" z="-2" />
		<voxel a="1.0" b="0.7608" g="0.298" r="0.2078" x="-9" y="-7" z="-2" />
		<voxel a="1.0" b="0.498" g="0.498" r="0.498" x="-8" y="-7" z="-2" />
		<voxel a="1.0" b="0.498" g="0.498" r="0.498" x="-7" y="-7" z="-2" />
		<voxel a="1.0" b="0.7608" g="0.298" r="0.2078" x="-6" y="-7" z="-2" />
		<voxel a="1.0" b="0.498" g="0.498" r="0.498" x="-5" y="-7" z="-2" />
		<voxel a="1.0" b="0.1647" g="0.2157" r="0.4431" x="-4" y="-7" z="-2" />
		<voxel a="1.0" b="0.1647" g="0.2157" r="0.4431" x="-11" y="-7" z="-3" />
		<voxel a="1.0" b="0.7608" g="0.298" r="0.2078" x="-10" y="-7" z="-3" />
		<voxel a="1.0" b="0.498" g="0.498" r="0.498" x="-9" y="-7" z="-3" />
		<voxel a="1.0" b="0.498" g="0.498" r="0.498" x="-8" y="-7" z="-3" />
		<voxel a="1.0" b="0.498" g="0.498" r="0.498" x="-7" y="-7" z="-3" />
		<voxel a="1.0" b="0.498" g="0.498" r="0.498" x="-6" y="-7" z="-3" />
		<voxel a="1.0" b="0.7608" g="0.298" r="0.2078" x="-5" y="-7" z="-3" />
		<voxel a="1.0" b="0.1647" g="0.2157" r="0.4431" x="-4" y="-7" z="-3" />
		<voxel a="1.0" b="0.1647" g="0.2157" r="0.4431" x="-11" y="-7" z="-4" />
		<voxel a="1.0" b="0.1647" g="0.2157" r="0.4431" x="-10" y="-7" z="-4" />
		<voxel a="1.0" b="0.1647" g="0.2157" r="0.4431" x="-9" y="-7" z="-4" />
		<voxel a="1.0" b="0.1647" g="0.2157" r="0.4431" x="-8" y="-7" z="-4" />
		<voxel a="1.0" b="0.1647" g="0.2157" r="0.4431" x="-7" y="-7" z="-4" />
		<voxel a="1.0" b="0.1647" g="0.2157" r="0.4431" x="-6" y="-7" z="-4" />
		<voxel a="1.0" b="0.1647" g="0.2157" r="0.4431" x="-5" y="-7" z="-4" />
		<voxel a="1.0" b="0.1647" g="0.2157" r="0.4431" x="-4" y="-7" z="-4" />
		<voxel a="1.0" b="0.1647" g="0.2157" r="0.4431" x="-11" y="-6" z="4" />
		<voxel a="1.0" b="0.498" g="0.498" r="0.498" x="-10" y="-6" z="4" />
		<voxel a="1.0" b="0.498" g="0.498" r="0.498" x="-9" y="-6" z="4" />
		<voxel a="1.0" b="0.498" g="0.498" r="0.498" x="-8" y="-6" z="4" />
		<voxel a="1.0" b="0.498" g="0.498" r="0.498" x="-7" y="-6" z="4" />
		<voxel a="1.0" b="0.498" g="0.498" r="0.498" x="-6" y="-6" z="4" />
		<voxel a="1.0" b="0.498" g="0.498" r="0.498" x="-5" y="-6" z="4" />
		<voxel a="1.0" b="0.1647" g="0.2157" r="0.4431" x="-4" y="-6" z="4" />
		<voxel a="1.0" b="0.498" g="0.498" r="0.498" x="-11" y="-6" z="3" />
		<voxel a="1.0" b="0.498" g="0.498" r="0.498" x="-4" y="-6" z="3" />
		<voxel a="1.0" b="0.498" g="0.498" r="0.498" x="-11" y="-6" z="2" />
		<voxel a="1.0" b="0.498" g="0.498" r="0.498" x="-4" y="-6" z="2" />
		<voxel a="1.0" b="0.498" g="0.498" r="0.498" x="-11" y="-6" z="1" />
		<voxel a="1.0" b="0.498" g="0.498" r="0.498" x="-4" y="-6" z="1" />
		<voxel a="1.0" b="0.498" g="0.498" r="0.498" x="-11" y="-6" z="0" />
		<voxel a="1.0" b="0.498" g="0.498" r="0.498" x="-4" y="-6" z="0" />
		<voxel a="1.0" b="0.498" g="0.498" r="0.498" x="-11" y="-6" z="-1" />
		<voxel a="1.0" b="0.498" g="0.498" r="0.498" x="-4" y="-6" z="-1" />
		<voxel a="1.0" b="0.498" g="0.498" r="0.498" x="-11" y="-6" z="-2" />
		<voxel a="1.0" b="0.498" g="0.498" r="0.498" x="-4" y="-6" z="-2" />
		<voxel a="1.0" b="0.498" g="0.498" r="0.498" x="-11" y="-6" z="-3" />
		<voxel a="1.0" b="0.498" g="0.498" r="0.498" x="-4" y="-6" z="-3" />
		<voxel a="1.0" b="0.1647" g="0.2157" r="0.4431" x="-11" y="-6" z="-4" />
		<voxel a="1.0" b="0.498" g="0.498" r="0.498" x="-10" y="-6" z="-4" />
		<voxel a="1.0" b="0.498" g="0.498" r="0.498" x="-9" y="-6" z="-4" />
		<voxel a="1.0" b="0.498" g="0.498" r="0.498" x="-8" y="-6" z="-4" />
		<voxel a="1.0" b="0.498" g="0.498" r="0.498" x="-7" y="-6" z="-4" />
		<voxel a="1.0" b="0.498" g="0.498" r="0.498" x="-6" y="-6" z="-4" />
		<voxel a="1.0" b="0.498" g="0.498" r="0.498" x="-5" y="-6" z="-4" />
		<voxel a="1.0" b="0.1647" g="0.2157" r="0.4431" x="-4" y="-6" z="-4" />
		<voxel a="1.0" b="0.1647" g="0.2157" r="0.4431" x="-11" y="-5" z="4" />
		<voxel a="1.0" b="0.498" g="0.498" r="0.498" x="-10" y="-5" z="4" />
		<voxel a="1.0" b="0.498" g="0.498" r="0.498" x="-9" y="-5" z="4" />
		<voxel a="1.0" b="0.498" g="0.498" r="0.498" x="-8" y="-5" z="4" />
		<voxel a="1.0" b="0.498" g="0.498" r="0.498" x="-7" y="-5" z="4" />
		<voxel a="1.0" b="0.498" g="0.498" r="0.498" x="-6" y="-5" z="4" />
		<voxel a="1.0" b="0.498" g="0.498" r="0.498" x="-5" y="-5" z="4" />
		<voxel a="1.0" b="0.1647" g="0.2157" r="0.4431" x="-4" y="-5" z="4" />
		<voxel a="1.0" b="0.498" g="0.498" r="0.498" x="-11" y="-5" z="3" />
		<voxel a="1.0" b="0.498" g="0.498" r="0.498" x="-4" y="-5" z="3" />
		<voxel a="1.0" b="0.498" g="0.498" r="0.498" x="-11" y="-5" z="2" />
		<voxel a="1.0" b="0.498" g="0.498" r="0.498" x="-4" y="-5" z="2" />
		<voxel a="1.0" b="0.498" g="0.498" r="0.498" x="-11" y="-5" z="1" />
		<voxel a="1.0" b="0.498" g="0.498" r="0.498" x="-4" y="-5" z="1" />
		<voxel a="1.0" b="0.498" g="0.498" r="0.498" x="-11" y="-5" z="0" />
		<voxel a="1.0" b="0.498" g="0.498" r="0.498" x="-4" y="-5" z="0" />
		<voxel a="1.0" b="0.498" g="0.498" r="0.498" x="-11" y="-5" z="-1" />
		<voxel a="1.0" b="0.498" g="0.498" r="0.498" x="-4" y="-5" z="-1" />
		<voxel a="1.0" b="0.498" g="0.498" r="0.498" x="-11" y="-5" z="-2" />
		<voxel a="1.0" b="0.498" g="0.498" r="0.498" x="-4" y="-5" z="-2" />
		<voxel a="1.0" b="0.498" g="0.498" r="0.498" x="-11" y="-5" z="-3" />
		<voxel a="1.0" b="0.498" g="0.498" r="0.498" x="-4" y="-5" z="-3" />
		<voxel a="1.0" b="0.1647" g="0.2157" r="0.4431" x="-11" y="-5" z="-4" />
		<voxel a="1.0" b="0.498" g="0.498" r="0.498" x="-10" y="-5" z="-4" />
		<voxel a="1.0" b="0.498" g="0.498" r="0.498" x="-9" y="-5" z="-4" />
		<voxel a="1.0" b="0.498" g="0.498" r="0.498" x="-8" y="-5" z="-4" />
		<voxel a="1.0" b="0.498" g="0.498" r="0.498" x="-7" y="-5" z="-4" />
		<voxel a="1.0" b="0.498" g="0.498" r="0.498" x="-6" y="-5" z="-4" />
		<voxel a="1.0" b="0.498" g="0.498" r="0.498" x="-5" y="-5" z="-4" />
		<voxel a="1.0" b="0.1647" g="0.2157" r="0.4431" x="-4" y="-5" z="-4" />
		<voxel a="1.0" b="0.1647" g="0.2157" r="0.4431" x="-11" y="-4" z="4" />
		<voxel a="1.0" b="0.1647" g="0.2157" r="0.4431" x="-10" y="-4" z="4" />
		<voxel a="1.0" b="0.1647" g="0.2157" r="0.4431" x="-9" y="-4" z="4" />
		<voxel a="1.0" b="0.1647" g="0.2157" r="0.4431" x="-8" y="-4" z="4" />
		<voxel a="1.0" b="0.1647" g="0.2157" r="0.4431" x="-7" y="-4" z="4" />
		<voxel a="1.0" b="0.1647" g="0.2157" r="0.4431" x="-6" y="-4" z="4" />
		<voxel a="1.0" b="0.1647" g="0.2157" r="0.4431" x="-5" y="-4" z="4" />
		<voxel a="1.0" b="0.1647" g="0.2157" r="0.4431" x="-4" y="-4" z="4" />
		<voxel a="1.0" b="0.498" g="0.498" r="0.498" x="-11" y="-4" z="3" />
		<voxel a="1.0" b="0.498" g="0.498" r="0.498" x="-4" y="-4" z="3" />
		<voxel a="1.0" b="0.498" g="0.498" r="0.498" x="-11" y="-4" z="2" />
		<voxel a="1.0" b="0.7608" g="0.298" r="0.2078" x="-4" y="-4" z="2" />
		<voxel a="1.0" b="0.498" g="0.498" r="0.498" x="-11" y="-4" z="1" />
		<voxel a="1.0" b="0.7608" g="0.298" r="0.2078" x="-4" y="-4" z="1" />
		<voxel a="1.0" b="0.498" g="0.498" r="0.498" x="-11" y="-4" z="0" />
		<voxel a="1.0" b="0.7608" g="0.298" r="0.2078" x="-4" y="-4" z="0" />
		<voxel a="1.0" b="0.498" g="0.498" r="0.498" x="-11" y="-4" z="-1" />
		<voxel a="1.0" b="0.7608" g="0.298" r="0.2078" x="-4" y="-4" z="-1" />
		<voxel a="1.0" b="0.498" g="0.498" r="0.498" x="-11" y="-4" z="-2" />
		<voxel a="1.0" b="0.7608" g="0.298" r="0.2078" x="-4" y="-4" z="-2" />
		<voxel a="1.0" b="0.498" g="0.498" r="0.498" x="-11" y="-4" z="-3" />
		<voxel a="1.0" b="0.498" g="0.498" r="0.498" x="-4" y="-4" z="-3" />
		<voxel a="1.0" b="0.1647" g="0.2157" r="0.4431" x="-11" y="-4" z="-4" />
		<voxel a="1.0" b="0.1647" g="0.2157" r="0.4431" x="-10" y="-4" z="-4" />
		<voxel a="1.0" b="0.1647" g="0.2157" r="0.4431" x="-9" y="-4" z="-4" />
		<voxel a="1.0" b="0.1647" g="0.2157" r="0.4431" x="-8" y="-4" z="-4" />
		<voxel a="1.0" b="0.1647" g="0.2157" r="0.4431" x="-7" y="-4" z="-4" />
		<voxel a="1.0" b="0.1647" g="0.2157" r="0.4431" x="-6" y="-4" z="-4" />
		<voxel a="1.0" b="0.1647" g="0.2157" r="0.4431" x="-5" y="-4" z="-4" />
		<voxel a="1.0" b="0.1647" g="0.2157" r="0.4431" x="-4" y="-4" z="-4" />
		<voxel a="1.0" b="0.1647" g="0.2157" r="0.4431" x="-11" y="-3" z="4" />
		<voxel a="1.0" b="0.1647" g="0.2157" r="0.4431" x="-10" y="-3" z="4" />
		<voxel a="1.0" b="0.1647" g="0.2157" r="0.4431" x="-9" y="-3" z="4" />
		<voxel a="1.0" b="1.0" g="0.7804" r="0.0" x="-8" y="-3" z="4" />
		<voxel a="1.0" b="1.0" g="0.7804" r="0.0" x="-7" y="-3" z="4" />
		<voxel a="1.0" b="0.1647" g="0.2157" r="0.4431" x="-6" y="-3" z="4" />
		<voxel a="1.0" b="0.1647" g="0.2157" r="0.4431" x="-5" y="-3" z="4" />
		<voxel a="1.0" b="0.1647" g="0.2157" r="0.4431" x="-4" y="-3" z="4" />
		<voxel a="1.0" b="0.498" g="0.498" r="0.498" x="-11" y="-3" z="3" />
		<voxel a="1.0" b="0.498" g="0.498" r="0.498" x="-4" y="-3" z="3" />
		<voxel a="1.0" b="0.498" g="0.498" r="0.498" x="-11" y="-3" z="2" />
		<voxel a="1.0" b="0.7608" g="0.298" r="0.2078" x="-4" y="-3" z="2" />
		<voxel a="1.0" b="0.498" g="0.498" r="0.498" x="-11" y="-3" z="1" />
		<voxel a="1.0" b="0.1294" g="0.1255" r="0.1294" x="-4" y="-3" z="1" />
		<voxel a="1.0" b="0.498" g="0.498" r="0.498" x="-11" y="-3" z="0" />
		<voxel a="1.0" b="0.1294" g="0.1255" r="0.1294" x="-4" y="-3" z="0" />
		<voxel a="1.0" b="0.498" g="0.498" r="0.498" x="-11" y="-3" z="-1" />
		<voxel a="1.0" b="0.1294" g="0.1255" r="0.1294" x="-4" y="-3" z="-1" />
		<voxel a="1.0" b="0.498" g="0.498" r="0.498" x="-11" y="-3" z="-2" />
		<voxel a="1.0" b="0.7608" g="0.298" r="0.2078" x="-4" y="-3" z="-2" />
		<voxel a="1.0" b="0.498" g="0.498" r="0.498" x="-11" y="-3" z="-3" />
		<voxel a="1.0" b="0.498" g="0.498" r="0.498" x="-4" y="-3" z="-3" />
		<voxel a="1.0" b="0.1647" g="0.2157" r="0.4431" x="-11" y="-3" z="-4" />
		<voxel a="1.0" b="0.1647" g="0.2157" r="0.4431" x="-10" y="-3" z="-4" />
		<voxel a="1.0" b="0.1647" g="0.2157" r="0.4431" x="-9" y="-3" z="-4" />
		<voxel a="1.0" b="1.0" g="0.7804" r="0.0" x="-8" y="-3" z="-4" />
		<voxel a="1.0" b="1.0" g="0.7804" r="0.0" x="-7" y="-3" z="-4" />
		<voxel a="1.0" b="0.1647" g="0.2157" r="0.4431" x="-6" y="-3" z="-4" />
		<voxel a="1.0" b="0.1647" g="0.2157" r="0.4431" x="-5" y="-3" z="-4" />
		<voxel a="1.0" b="0.1647" g="0.2157" r="0.4431" x="-4" y="-3" z="-4" />
		<voxel a="1.0" b="0.1647" g="0.2157" r="0.4431" x="-11" y="-2" z="4" />
		<voxel a="1.0" b="0.1647" g="0.2157" r="0.4431" x="-10" y="-2" z="4" />
		<voxel a="1.0" b="0.1647" g="0.2157" r="0.4431" x="-9" y="-2" z="4" />
		<voxel a="1.0" b="1.0" g="0.7804" r="0.0" x="-8" y="-2" z="4" />
		<voxel a="1.0" b="1.0" g="0.7804" r="0.0" x="-7" y="-2" z="4" />
		<voxel a="1.0" b="0.1647" g="0.2157" r="0.4431" x="-6" y="-2" z="4" />
		<voxel a="1.0" b="0.1647" g="0.2157" r="0.4431" x="-5" y="-2" z="4" />
		<voxel a="1.0" b="0.1647" g="0.2157" r="0.4431" x="-4" y="-2" z="4" />
		<voxel a="1.0" b="0.498" g="0.498" r="0.498" x="-11" y="-2" z="3" />
		<voxel a="1.0" b="0.498" g="0.498" r="0.498" x="-4" y="-2" z="3" />
		<voxel a="1.0" b="0.498" g="0.498" r="0.498" x="-11" y="-2" z="2" />
		<voxel a="1.0" b="0.7608" g="0.298" r="0.2078" x="-4" y="-2" z="2" />
		<voxel a="1.0" b="0.498" g="0.498" r="0.498" x="-11" y="-2" z="1" />
		<voxel a="1.0" b="0.1294" g="0.1255" r="0.1294" x="-4" y="-2" z="1" />
		<voxel a="1.0" b="0.498" g="0.498" r="0.498" x="-11" y="-2" z="0" />
		<voxel a="1.0" b="0.498" g="0.498" r="0.498" x="-4" y="-2" z="0" />
		<voxel a="1.0" b="0.7608" g="0.298" r="0.2078" x="-3" y="-2" z="0" />
		<voxel a="1.0" b="0.7608" g="0.298" r="0.2078" x="-2" y="-2" z="0" />
		<voxel a="1.0" b="0.7608" g="0.298" r="0.2078" x="-1" y="-2" z="0" />
		<voxel a="1.0" b="0.498" g="0.498" r="0.498" x="-11" y="-2" z="-1" />
		<voxel a="1.0" b="0.1294" g="0.1255" r="0.1294" x="-4" y="-2" z="-1" />
		<voxel a="1.0" b="0.498" g="0.498" r="0.498" x="-11" y="-2" z="-2" />
		<voxel a="1.0" b="0.7608" g="0.298" r="0.2078" x="-4" y="-2" z="-2" />
		<voxel a="1.0" b="0.498" g="0.498" r="0.498" x="-11" y="-2" z="-3" />
		<voxel a="1.0" b="0.498" g="0.498" r="0.498" x="-4" y="-2" z="-3" />
		<voxel a="1.0" b="0.1647" g="0.2157" r="0.4431" x="-11" y="-2" z="-4" />
		<voxel a="1.0" b="0.1647" g="0.2157" r="0.4431" x="-10" y="-2" z="-4" />
		<voxel a="1.0" b="0.1647" g="0.2157" r="0.4431" x="-9" y="-2" z="-4" />
		<voxel a="1.0" b="1.0" g="0.7804" r="0.0" x="-8" y="-2" z="-4" />
		<voxel a="1.0" b="1.0" g="0.7804" r="0.0" x="-7" y="-2" z="-4" />
		<voxel a="1.0" b="0.1647" g="0.2157" r="0.4431" x="-6" y="-2" z="-4" />
		<voxel a="1.0" b="0.1647" g="0.2157" r="0.4431" x="-5" y="-2" z="-4" />
		<voxel a="1.0" b="0.1647" g="0.2157" r="0.4431" x="-4" y="-2" z="-4" />
		<voxel a="1.0" b="0.1647" g="0.2157" r="0.4431" x="-11" y="-1" z="4" />
		<voxel a="1.0" b="1.0" g="0.7804" r="0.0" x="-10" y="-1" z="4" />
		<voxel a="1.0" b="1.0" g="0.7804" r="0.0" x="-9" y="-1" z="4" />
		<voxel a="1.0" b="1.0" g="0.7804" r="0.0" x="-8" y="-1" z="4" />
		<voxel a="1.0" b="1.0" g="0.7804" r="0.0" x="-7" y="-1" z="4" />
		<voxel a="1.0" b="1.0" g="0.7804" r="0.0" x="-6" y="-1" z="4" />
		<voxel a="1.0" b="1.0" g="0.7804" r="0.0" x="-5" y="-1" z="4" />
		<voxel a="1.0" b="0.1647" g="0.2157" r="0.4431" x="-4" y="-1" z="4" />
		<voxel a="1.0" b="0.498" g="0.498" r="0.498" x="-11" y="-1" z="3" />
		<voxel a="1.0" b="0.498" g="0.498" r="0.498" x="-4" y="-1" z="3" />
		<voxel a="1.0" b="0.498" g="0.498" r="0.498" x="-11" y="-1" z="2" />
		<voxel a="1.0" b="0.7608" g="0.298" r="0.2078" x="-4" y="-1" z="2" />
		<voxel a="1.0" b="0.498" g="0.498" r="0.498" x="-11" y="-1" z="1" />
		<voxel a="1.0" b="0.1294" g="0.1255" r="0.1294" x="-4" y="-1" z="1" />
		<voxel a="1.0" b="0.498" g="0.498" r="0.498" x="-11" y="-1" z="0" />
		<voxel a="1.0" b="0.1294" g="0.1255" r="0.1294" x="-4" y="-1" z="0" />
		<voxel a="1.0" b="0.7608" g="0.298" r="0.2078" x="-1" y="-1" z="0" />
		<voxel a="1.0" b="0.498" g="0.498" r="0.498" x="-11" y="-1" z="-1" />
		<voxel a="1.0" b="0.1294" g="0.1255" r="0.1294" x="-4" y="-1" z="-1" />
		<voxel a="1.0" b="0.498" g="0.498" r="0.498" x="-11" y="-1" z="-2" />
		<voxel a="1.0" b="0.7608" g="0.298" r="0.2078" x="-4" y="-1" z="-2" />
		<voxel a="1.0" b="0.498" g="0.498" r="0.498" x="-11" y="-1" z="-3" />
		<voxel a="1.0" b="0.498" g="0.498" r="0.498" x="-4" y="-1" z="-3" />
		<voxel a="1.0" b="0.1647" g="0.2157" r="0.4431" x="-11" y="-1" z="-4" />
		<voxel a="1.0" b="1.0" g="0.7804" r="0.0" x="-10" y="-1" z="-4" />
		<voxel a="1.0" b="1.0" g="0.7804" r="0.0" x="-9" y="-1" z="-4" />
		<voxel a="1.0" b="1.0" g="0.7804" r="0.0" x="-8" y="-1" z="-4" />
		<voxel a="1.0" b="1.0" g="0.7804" r="0.0" x="-7" y="-1" z="-4" />
		<voxel a="1.0" b="1.0" g="0.7804" r="0.0" x="-6" y="-1" z="-4" />
		<voxel a="1.0" b="1.0" g="0.7804" r="0.0" x="-5" y="-1" z="-4" />
		<voxel a="1.0" b="0.1647" g="0.2157" r="0.4431" x="-4" y="-1" z="-4" />
		<voxel a="1.0" b="0.1647" g="0.2157" r="0.4431" x="-11" y="0" z="4" />
		<voxel a="1.0" b="1.0" g="0.7804" r="0.0" x="-10" y="0" z="4" />
		<voxel a="1.0" b="1.0" g="0.7804" r="0.0" x="-9" y="0" z="4" />
		<voxel a="1.0" b="1.0" g="0.7804" r="0.0" x="-8" y="0" z="4" />
		<voxel a="1.0" b="1.0" g="0.7804" r="0.0" x="-7" y="0" z="4" />
		<voxel a="1.0" b="1.0" g="0.7804" r="0.0" x="-6" y="0" z="4" />
		<voxel a="1.0" b="1.0" g="0.7804" r="0.0" x="-5" y="0" z="4" />
		<voxel a="1.0" b="0.1647" g="0.2157" r="0.4431" x="-4" y="0" z="4" />
		<voxel a="1.0" b="0.498" g="0.498" r="0.498" x="-11" y="0" z="3" />
		<voxel a="1.0" b="0.498" g="0.498" r="0.498" x="-4" y="0" z="3" />
		<voxel a="1.0" b="0.498" g="0.498" r="0.498" x="-11" y="0" z="2" />
		<voxel a="1.0" b="0.7608" g="0.298" r="0.2078" x="-4" y="0" z="2" />
		<voxel a="1.0" b="0.498" g="0.498" r="0.498" x="-11" y="0" z="1" />
		<voxel a="1.0" b="0.1294" g="0.1255" r="0.1294" x="-4" y="0" z="1" />
		<voxel a="1.0" b="0.498" g="0.498" r="0.498" x="-11" y="0" z="0" />
		<voxel a="1.0" b="0.1294" g="0.1255" r="0.1294" x="-4" y="0" z="0" />
		<voxel a="1.0" b="0.7608" g="0.298" r="0.2078" x="-1" y="0" z="0" />
		<voxel a="1.0" b="0.498" g="0.498" r="0.498" x="-11" y="0" z="-1" />
		<voxel a="1.0" b="0.1294" g="0.1255" r="0.1294" x="-4" y="0" z="-1" />
		<voxel a="1.0" b="0.498" g="0.498" r="0.498" x="-11" y="0" z="-2" />
		<voxel a="1.0" b="0.7608" g="0.298" r="0.2078" x="-4" y="0" z="-2" />
		<voxel a="1.0" b="0.498" g="0.498" r="0.498" x="-11" y="0" z="-3" />
		<voxel a="1.0" b="0.498" g="0.498" r="0.498" x="-4" y="0" z="-3" />
		<voxel a="1.0" b="0.1647" g="0.2157" r="0.4431" x="-11" y="0" z="-4" />
		<voxel a="1.0" b="1.0" g="0.7804" r="0.0" x="-10" y="0" z="-4" />
		<voxel a="1.0" b="1.0" g="0.7804" r="0.0" x="-9" y="0" z="-4" />
		<voxel a="1.0" b="1.0" g="0.7804" r="0.0" x="-8" y="0" z="-4" />
		<voxel a="1.0" b="1.0" g="0.7804" r="0.0" x="-7" y="0" z="-4" />
		<voxel a="1.0" b="1.0" g="0.7804" r="0.0" x="-6" y="0" z="-4" />
		<voxel a="1.0" b="1.0" g="0.7804" r="0.0" x="-5" y="0" z="-4" />
		<voxel a="1.0" b="0.1647" g="0.2157" r="0.4431" x="-4" y="0" z="-4" />
		<voxel a="1.0" b="0.1647" g="0.2157" r="0.4431" x="-11" y="1" z="4" />
		<voxel a="1.0" b="0.1647" g="0.2157" r="0.4431" x="-10" y="1" z="4" />
		<voxel a="1.0" b="0.1647" g="0.2157" r="0.4431" x="-9" y="1" z="4" />
		<voxel a="1.0" b="1.0" g="0.7804" r="0.0" x="-8" y="1" z="4" />
		<voxel a="1.0" b="1.0" g="0.7804" r="0.0" x="-7" y="1" z="4" />
		<voxel a="1.0" b="0.1647" g="0.2157" r="0.4431" x="-6" y="1" z="4" />
		<voxel a="1.0" b="0.1647" g="0.2157" r="0.4431" x="-5" y="1" z="4" />
		<voxel a="1.0" b="0.1647" g="0.2157" r="0.4431" x="-4" y="1" z="4" />
		<voxel a="1.0" b="0.498" g="0.498" r="0.498" x="-11" y="1" z="3" />
		<voxel a="1.0" b="0.498" g="0.498" r="0.498" x="-4" y="1" z="3" />
		<voxel a="1.0" b="0.498" g="0.498" r="0.498" x="-11" y="1" z="2" />
		<voxel a="1.0" b="0.7608" g="0.298" r="0.2078" x="-4" y="1" z="2" />
		<voxel a="1.0" b="0.498" g="0.498" r="0.498" x="-11" y="1" z="1" />
		<voxel a="1.0" b="0.1294" g="0.1255" r="0.1294" x="-4" y="1" z="1" />
		<voxel a="1.0" b="0.498" g="0.498" r="0.498" x="-11" y="1" z="0" />
		<voxel a="1.0" b="0.498" g="0.498" r="0.498" x="-4" y="1" z="0" />
		<voxel a="1.0" b="0.7608" g="0.298" r="0.2078" x="-3" y="1" z="0" />
		<voxel a="1.0" b="0.7608" g="0.298" r="0.2078" x="-2" y="1" z="0" />
		<voxel a="1.0" b="0.7608" g="0.298" r="0.2078" x="-1" y="1" z="0" />
		<voxel a="1.0" b="0.498" g="0.498" r="0.498" x="-11" y="1" z="-1" />
		<voxel a="1.0" b="0.1294" g="0.1255" r="0.1294" x="-4" y="1" z="-1" />
		<voxel a="1.0" b="0.498" g="0.498" r="0.498" x="-11" y="1" z="-2" />
		<voxel a="1.0" b="0.7608" g="0.298" r="0.2078" x="-4" y="1" z="-2" />
		<voxel a="1.0" b="0.498" g="0.498" r="0.498" x="-11" y="1" z="-3" />
		<voxel a="1.0" b="0.498" g="0.498" r="0.498" x="-4" y="1" z="-3" />
		<voxel a="1.0" b="0.1647" g="0.2157" r="0.4431" x="-11" y="1" z="-4" />
		<voxel a="1.0" b="0.1647" g="0.2157" r="0.4431" x="-10" y="1" z="-4" />
		<voxel a="1.0" b="0.1647" g="0.2157" r="0.4431" x="-9" y="1" z="-4" />
		<voxel a="1.0" b="1.0" g="0.7804" r="0.0" x="-8" y="1" z="-4" />
		<voxel a="1.0" b="1.0" g="0.7804" r="0.0" x="-7" y="1" z="-4" />
		<voxel a="1.0" b="0.1647" g="0.2157" r="0.4431" x="-6" y="1" z="-4" />
		<voxel a="1.0" b="0.1647" g="0.2157" r="0.4431" x="-5" y="1" z="-4" />
		<voxel a="1.0" b="0.1647" g="0.2157" r="0.4431" x="-4" y="1" z="-4" />
		<voxel a="1.0" b="0.1647" g="0.2157" r="0.4431" x="-11" y="2" z="4" />
		<voxel a="1.0" b="0.1647" g="0.2157" r="0.4431" x="-10" y="2" z="4" />
		<voxel a="1.0" b="0.1647" g="0.2157" r="0.4431" x="-9" y="2" z="4" />
		<voxel a="1.0" b="1.0" g="0.7804" r="0.0" x="-8" y="2" z="4" />
		<voxel a="1.0" b="1.0" g="0.7804" r="0.0" x="-7" y="2" z="4" />
		<voxel a="1.0" b="0.1647" g="0.2157" r="0.4431" x="-6" y="2" z="4" />
		<voxel a="1.0" b="0.1647" g="0.2157" r="0.4431" x="-5" y="2" z="4" />
		<voxel a="1.0" b="0.1647" g="0.2157" r="0.4431" x="-4" y="2" z="4" />
		<voxel a="1.0" b="0.498" g="0.498" r="0.498" x="-11" y="2" z="3" />
		<voxel a="1.0" b="0.498" g="0.498" r="0.498" x="-4" y="2" z="3" />
		<voxel a="1.0" b="0.498" g="0.498" r="0.498" x="-11" y="2" z="2" />
		<voxel a="1.0" b="0.7608" g="0.298" r="0.2078" x="-4" y="2" z="2" />
		<voxel a="1.0" b="0.498" g="0.498" r="0.498" x="-11" y="2" z="1" />
		<voxel a="1.0" b="0.1294" g="0.1255" r="0.1294" x="-4" y="2" z="1" />
		<voxel a="1.0" b="0.498" g="0.498" r="0.498" x="-11" y="2" z="0" />
		<voxel a="1.0" b="0.1294" g="0.1255" r="0.1294" x="-4" y="2" z="0" />
		<voxel a="1.0" b="0.498" g="0.498" r="0.498" x="-11" y="2" z="-1" />
		<voxel a="1.0" b="0.1294" g="0.1255" r="0.1294" x="-4" y="2" z="-1" />
		<voxel a="1.0" b="0.498" g="0.498" r="0.498" x="-11" y="2" z="-2" />
		<voxel a="1.0" b="0.7608" g="0.298" r="0.2078" x="-4" y="2" z="-2" />
		<voxel a="1.0" b="0.498" g="0.498" r="0.498" x="-11" y="2" z="-3" />
		<voxel a="1.0" b="0.498" g="0.498" r="0.498" x="-4" y="2" z="-3" />
		<voxel a="1.0" b="0.1647" g="0.2157" r="0.4431" x="-11" y="2" z="-4" />
		<voxel a="1.0" b="0.1647" g="0.2157" r="0.4431" x="-10" y="2" z="-4" />
		<voxel a="1.0" b="0.1647" g="0.2157" r="0.4431" x="-9" y="2" z="-4" />
		<voxel a="1.0" b="1.0" g="0.7804" r="0.0" x="-8" y="2" z="-4" />
		<voxel a="1.0" b="1.0" g="0.7804" r="0.0" x="-7" y="2" z="-4" />
		<voxel a="1.0" b="0.1647" g="0.2157" r="0.4431" x="-6" y="2" z="-4" />
		<voxel a="1.0" b="0.1647" g="0.2157" r="0.4431" x="-5" y="2" z="-4" />
		<voxel a="1.0" b="0.1647" g="0.2157" r="0.4431" x="-4" y="2" z="-4" />
		<voxel a="1.0" b="0.1647" g="0.2157" r="0.4431" x="-11" y="3" z="4" />
		<voxel a="1.0" b="0.1647" g="0.2157" r="0.4431" x="-10" y="3" z="4" />
		<voxel a="1.0" b="0.1647" g="0.2157" r="0.4431" x="-9" y="3" z="4" />
		<voxel a="1.0" b="0.1647" g="0.2157" r="0.4431" x="-8" y="3" z="4" />
		<voxel a="1.0" b="0.1647" g="0.2157" r="0.4431" x="-7" y="3" z="4" />
		<voxel a="1.0" b="0.1647" g="0.2157" r="0.4431" x="-6" y="3" z="4" />
		<voxel a="1.0" b="0.1647" g="0.2157" r="0.4431" x="-5" y="3" z="4" />
		<voxel a="1.0" b="0.1647" g="0.2157" r="0.4431" x="-4" y="3" z="4" />
		<voxel a="1.0" b="0.498" g="0.498" r="0.498" x="-11" y="3" z="3" />
		<voxel a="1.0" b="0.498" g="0.498" r="0.498" x="-4" y="3" z="3" />
		<voxel a="1.0" b="0.498" g="0.498" r="0.498" x="-11" y="3" z="2" />
		<voxel a="1.0" b="0.7608" g="0.298" r="0.2078" x="-4" y="3" z="2" />
		<voxel a="1.0" b="0.498" g="0.498" r="0.498" x="-11" y="3" z="1" />
		<voxel a="1.0" b="0.7608" g="0.298" r="0.2078" x="-4" y="3" z="1" />
		<voxel a="1.0" b="0.498" g="0.498" r="0.498" x="-11" y="3" z="0" />
		<voxel a="1.0" b="0.7608" g="0.298" r="0.2078" x="-4" y="3" z="0" />
		<voxel a="1.0" b="0.498" g="0.498" r="0.498" x="-11" y="3" z="-1" />
		<voxel a="1.0" b="0.7608" g="0.298" r="0.2078" x="-4" y="3" z="-1" />
		<voxel a="1.0" b="0.498" g="0.498" r="0.498" x="-11" y="3" z="-2" />
		<voxel a="1.0" b="0.7608" g="0.298" r="0.2078" x="-4" y="3" z="-2" />
		<voxel a="1.0" b="0.498" g="0.498" r="0.498" x="-11" y="3" z="-3" />
		<voxel a="1.0" b="0.498" g="0.498" r="0.498" x="-4" y="3" z="-3" />
		<voxel a="1.0" b="0.1647" g="0.2157" r="0.4431" x="-11" y="3" z="-4" />
		<voxel a="1.0" b="0.1647" g="0.2157" r="0.4431" x="-10" y="3" z="-4" />
		<voxel a="1.0" b="0.1647" g="0.2157" r="0.4431" x="-9" y="3" z="-4" />
		<voxel a="1.0" b="0.1647" g="0.2157" r="0.4431" x="-8" y="3" z="-4" />
		<voxel a="1.0" b="0.1647" g="0.2157" r="0.4431" x="-7" y="3" z="-4" />
		<voxel a="1.0" b="0.1647" g="0.2157" r="0.4431" x="-6" y="3" z="-4" />
		<voxel a="1.0" b="0.1647" g="0.2157" r="0.4431" x="-5" y="3" z="-4" />
		<voxel a="1.0" b="0.1647" g="0.2157" r="0.4431" x="-4" y="3" z="-4" />
		<voxel a="1.0" b="0.1647" g="0.2157" r="0.4431" x="-11" y="4" z="4" />
		<voxel a="1.0" b="0.498" g="0.498" r="0.498" x="-10" y="4" z="4" />
		<voxel a="1.0" b="0.498" g="0.498" r="0.498" x="-9" y="4" z="4" />
		<voxel a="1.0" b="0.498" g="0.498" r="0.498" x="-8" y="4" z="4" />
		<voxel a="1.0" b="0.498" g="0.498" r="0.498" x="-7" y="4" z="4" />
		<voxel a="1.0" b="0.498" g="0.498" r="0.498" x="-6" y="4" z="4" />
		<voxel a="1.0" b="0.498" g="0.498" r="0.498" x="-5" y="4" z="4" />
		<voxel a="1.0" b="0.1647" g="0.2157" r="0.4431" x="-4" y="4" z="4" />
		<voxel a="1.0" b="0.498" g="0.498" r="0.498" x="-11" y="4" z="3" />
		<voxel a="1.0" b="0.498" g="0.498" r="0.498" x="-4" y="4" z="3" />
		<voxel a="1.0" b="0.498" g="0.498" r="0.498" x="-11" y="4" z="2" />
		<voxel a="1.0" b="0.498" g="0.498" r="0.498" x="-4" y="4" z="2" />
		<voxel a="1.0" b="0.498" g="0.498" r="0.498" x="-11" y="4" z="1" />
		<voxel a="1.0" b="0.498" g="0.498" r="0.498" x="-4" y="4" z="1" />
		<voxel a="1.0" b="0.498" g="0.498" r="0.498" x="-11" y="4" z="0" />
		<voxel a="1.0" b="0.498" g="0.498" r="0.498" x="-4" y="4" z="0" />
		<voxel a="1.0" b="0.498" g="0.498" r="0.498" x="-11" y="4" z="-1" />
		<voxel a="1.0" b="0.498" g="0.498" r="0.498" x="-4" y="4" z="-1" />
		<voxel a="1.0" b="0.498" g="0.498" r="0.498" x="-11" y="4" z="-2" />
		<voxel a="1.0" b="0.498" g="0.498" r="0.498" x="-4" y="4" z="-2" />
		<voxel a="1.0" b="0.498" g="0.498" r="0.498" x="-11" y="4" z="-3" />
		<voxel a="1.0" b="0.498" g="0.498" r="0.498" x="-4" y="4" z="-3" />
		<voxel a="1.0" b="0.1647" g="0.2157" r="0.4431" x="-11" y="4" z="-4" />
		<voxel a="1.0" b="0.498" g="0.498" r="0.498" x="-10" y="4" z="-4" />
		<voxel a="1.0" b="0.498" g="0.498" r="0.498" x="-9" y="4" z="-4" />
		<voxel a="1.0" b="0.498" g="0.498" r="0.498" x="-8" y="4" z="-4" />
		<voxel a="1.0" b="0.498" g="0.498" r="0.498" x="-7" y="4" z="-4" />
		<voxel a="1.0" b="0.498" g="0.498" r="0.498" x="-6" y="4" z="-4" />
		<voxel a="1.0" b="0.498" g="0.498" r="0.498" x="-5" y="4" z="-4" />
		<voxel a="1.0" b="0.1647" g="0.2157" r="0.4431" x="-4" y="4" z="-4" />
		<voxel a="1.0" b="0.1647" g="0.2157" r="0.4431" x="-11" y="5" z="4" />
		<voxel a="1.0" b="0.498" g="0.498" r="0.498" x="-10" y="5" z="4" />
		<voxel a="1.0" b="0.498" g="0.498" r="0.498" x="-9" y="5" z="4" />
		<voxel a="1.0" b="0.498" g="0.498" r="0.498" x="-8" y="5" z="4" />
		<voxel a="1.0" b="0.498" g="0.498" r="0.498" x="-7" y="5" z="4" />
		<voxel a="1.0" b="0.498" g="0.498" r="0.498" x="-6" y="5" z="4" />
		<voxel a="1.0" b="0.498" g="0.498" r="0.498" x="-5" y="5" z="4" />
		<voxel a="1.0" b="0.1647" g="0.2157" r="0.4431" x="-4" y="5" z="4" />
		<voxel a="1.0" b="0.498" g="0.498" r="0.498" x="-11" y="5" z="3" />
		<voxel a="1.0" b="0.498" g="0.498" r="0.498" x="-4" y="5" z="3" />
		<voxel a="1.0" b="0.498" g="0.498" r="0.498" x="-11" y="5" z="2" />
		<voxel a="1.0" b="0.498" g="0.498" r="0.498" x="-4" y="5" z="2" />
		<voxel a="1.0" b="0.498" g="0.498" r="0.498" x="-11" y="5" z="1" />
		<voxel a="1.0" b="0.498" g="0.498" r="0.498" x="-4" y="5" z="1" />
		<voxel a="1.0" b="0.498" g="0.498" r="0.498" x="-11" y="5" z="0" />
		<voxel a="1.0" b="0.498" g="0.498" r="0.498" x="-4" y="5" z="0" />
		<voxel a="1.0" b="0.498" g="0.498" r="0.498" x="-11" y="5" z="-1" />
		<voxel a="1.0" b="0.498" g="0.498" r="0.498" x="-4" y="5" z="-1" />
		<voxel a="1.0" b="0.498" g="0.498" r="0.498" x="-11" y="5" z="-2" />
		<voxel a="1.0" b="0.498" g="0.498" r="0.498" x="-4" y="5" z="-2" />
		<voxel a="1.0" b="0.498" g="0.498" r="0.498" x="-11" y="5" z="-3" />
		<voxel a="1.0" b="0.498" g="0.498" r="0.498" x="-4" y="5" z="-3" />
		<voxel a="1.0" b="0.1647" g="0.2157" r="0.4431" x="-11" y="5" z="-4" />
		<voxel a="1.0" b="0.498" g="0.498" r="0.498" x="-10" y="5" z="-4" />
		<voxel a="1.0" b="0.498" g="0.498" r="0.498" x="-9" y="5" z="-4" />
		<voxel a="1.0" b="0.498" g="0.498" r="0.498" x="-8" y="5" z="-4" />
		<voxel a="1.0" b="0.498" g="0.498" r="0.498" x="-7" y="5" z="-4" />
		<voxel a="1.0" b="0.498" g="0.498" r="0.498" x="-6" y="5" z="-4" />
		<voxel a="1.0" b="0.498" g="0.498" r="0.498" x="-5" y="5" z="-4" />
		<voxel a="1.0" b="0.1647" g="0.2157" r="0.4431" x="-4" y="5" z="-4" />
		<voxel a="1.0" b="0.1647" g="0.2157" r="0.4431" x="-11" y="6" z="4" />
		<voxel a="1.0" b="0.1647" g="0.2157" r="0.4431" x="-10" y="6" z="4" />
		<voxel a="1.0" b="0.1647" g="0.2157" r="0.4431" x="-9" y="6" z="4" />
		<voxel a="1.0" b="0.1647" g="0.2157" r="0.4431" x="-8" y="6" z="4" />
		<voxel a="1.0" b="0.1647" g="0.2157" r="0.4431" x="-7" y="6" z="4" />
		<voxel a="1.0" b="0.1647" g="0.2157" r="0.4431" x="-6" y="6" z="4" />
		<voxel a="1.0" b="0.1647" g="0.2157" r="0.4431" x="-5" y="6" z="4" />
		<voxel a="1.0" b="0.1647" g="0.2157" r="0.4431" x="-4" y="6" z="4" />
		<voxel a="1.0" b="0.1647" g="0.2157" r="0.4431" x="-11" y="6" z="3" />
		<voxel a="1.0" b="0.7608" g="0.298" r="0.2078" x="-10" y="6" z="3" />
		<voxel a="1.0" b="0.498" g="0.498" r="0.498" x="-9" y="6" z="3" />
		<voxel a="1.0" b="0.498" g="0.498" r="0.498" x="-8" y="6" z="3" />
		<voxel a="1.0" b="0.498" g="0.498" r="0.498" x="-7" y="6" z="3" />
		<voxel a="1.0" b="0.498" g="0.498" r="0.498" x="-6" y="6" z="3" />
		<voxel a="1.0" b="0.7608" g="0.298" r="0.2078" x="-5" y="6" z="3" />
		<voxel a="1.0" b="0.1647" g="0.2157" r="0.4431" x="-4" y="6" z="3" />
		<voxel a="1.0" b="0.1647" g="0.2157" r="0.4431" x="-11" y="6" z="2" />
		<voxel a="1.0" b="0.498" g="0.498" r="0.498" x="-10" y="6" z="2" />
		<voxel a="1.0" b="0.7608" g="0.298" r="0.2078" x="-9" y="6" z="2" />
		<voxel a="1.0" b="0.498" g="0.498" r="0.498" x="-8" y="6" z="2" />
		<voxel a="1.0" b="0.498" g="0.498" r="0.498" x="-7" y="6" z="2" />
		<voxel a="1.0" b="0.7608" g="0.298" r="0.2078" x="-6" y="6" z="2" />
		<voxel a="1.0" b="0.498" g="0.498" r="0.498" x="-5" y="6" z="2" />
		<voxel a="1.0" b="0.1647" g="0.2157" r="0.4431" x="-4" y="6" z="2" />
		<voxel a="1.0" b="0.1647" g="0.2157" r="0.4431" x="-11" y="6" z="1" />
		<voxel a="1.0" b="0.498" g="0.498" r="0.498" x="-10" y="6" z="1" />
		<voxel a="1.0" b="0.498" g="0.498" r="0.498" x="-9" y="6" z="1" />
		<voxel a="1.0" b="0.7608" g="0.298" r="0.2078" x="-8" y="6" z="1" />
		<voxel a="1.0" b="0.7608" g="0.298" r="0.2078" x="-7" y="6" z="1" />
		<voxel a="1.0" b="0.498" g="0.498" r="0.498" x="-6" y="6" z="1" />
		<voxel a="1.0" b="0.498" g="0.498" r="0.498" x="-5" y="6" z="1" />
		<voxel a="1.0" b="0.1647" g="0.2157" r="0.4431" x="-4" y="6" z="1" />
		<voxel a="1.0" b="0.1647" g="0.2157" r="0.4431" x="-11" y="6" z="0" />
		<voxel a="1.0" b="0.498" g="0.498" r="0.498" x="-10" y="6" z="0" />
		<voxel a="1.0" b="0.498" g="0.498" r="0.498" x="-9" y="6" z="0" />
		<voxel a="1.0" b="0.8039" g="0.1686" r="0.749" x="-8" y="6" z="0" />
		<voxel a="1.0" b="0.8039" g="0.1686" r="0.749" x="-7" y="6" z="0" />
		<voxel a="1.0" b="0.498" g="0.498" r="0.498" x="-6" y="6" z="0" />
		<voxel a="1.0" b="0.498" g="0.498" r="0.498" x="-5" y="6" z="0" />
		<voxel a="1.0" b="0.1647" g="0.2157" r="0.4431" x="-4" y="6" z="0" />
		<voxel a="1.0" b="0.1647" g="0.2157" r="0.4431" x="-11" y="6" z="-1" />
		<voxel a="1.0" b="0.498" g="0.498" r="0.498" x="-10" y="6" z="-1" />
		<voxel a="1.0" b="0.498" g="0.498" r="0.498" x="-9" y="6" z="-1" />
		<voxel a="1.0" b="0.7608" g="0.298" r="0.2078" x="-8" y="6" z="-1" />
		<voxel a="1.0" b="0.7608" g="0.298" r="0.2078" x="-7" y="6" z="-1" />
		<voxel a="1.0" b="0.498" g="0.498" r="0.498" x="-6" y="6" z="-1" />
		<voxel a="1.0" b="0.498" g="0.498" r="0.498" x="-5" y="6" z="-1" />
		<voxel a="1.0" b="0.1647" g="0.2157" r="0.4431" x="-4" y="6" z="-1" />
		<voxel a="1.0" b="0.1647" g="0.2157" r="0.4431" x="-11" y="6" z="-2" />
		<voxel a="1.0" b="0.498" g="0.498" r="0.498" x="-10" y="6" z="-2" />
		<voxel a="1.0" b="0.7608" g="0.298" r="0.2078" x="-9" y="6" z="-2" />
		<voxel a="1.0" b="0.498" g="0.498" r="0.498" x="-8" y="6" z="-2" />
		<voxel a="1.0" b="0.498" g="0.498" r="0.498" x="-7" y="6" z="-2" />
		<voxel a="1.0" b="0.7608" g="0.298" r="0.2078" x="-6" y="6" z="-2" />
		<voxel a="1.0" b="0.498" g="0.498" r="0.498" x="-5" y="6" z="-2" />
		<voxel a="1.0" b="0.1647" g="0.2157" r="0.4431" x="-4" y="6" z="-2" />
		<voxel a="1.0" b="0.1647" g="0.2157" r="0.4431" x="-11" y="6" z="-3" />
		<voxel a="1.0" b="0.7608" g="0.298" r="0.2078" x="-10" y="6" z="-3" />
		<voxel a="1.0" b="0.498" g="0.498" r="0.498" x="-9" y="6" z="-3" />
		<voxel a="1.0" b="0.498" g="0.498" r="0.498" x="-8" y="6" z="-3" />
		<voxel a="1.0" b="0.498" g="0.498" r="0.498" x="-7" y="6" z="-3" />
		<voxel a="1.0" b="0.498" g="0.498" r="0.498" x="-6" y="6" z="-3" />
		<voxel a="1.0" b="0.7608" g="0.298" r="0.2078" x="-5" y="6" z="-3" />
		<voxel a="1.0" b="0.1647" g="0.2157" r="0.4431" x="-4" y="6" z="-3" />
		<voxel a="1.0" b="0.1647" g="0.2157" r="0.4431" x="-11" y="6" z="-4" />
		<voxel a="1.0" b="0.1647" g="0.2157" r="0.4431" x="-10" y="6" z="-4" />
		<voxel a="1.0" b="0.1647" g="0.2157" r="0.4431" x="-9" y="6" z="-4" />
		<voxel a="1.0" b="0.1647" g="0.2157" r="0.4431" x="-8" y="6" z="-4" />
		<voxel a="1.0" b="0.1647" g="0.2157" r="0.4431" x="-7" y="6" z="-4" />
		<voxel a="1.0" b="0.1647" g="0.2157" r="0.4431" x="-6" y="6" z="-4" />
		<voxel a="1.0" b="0.1647" g="0.2157" r="0.4431" x="-5" y="6" z="-4" />
		<voxel a="1.0" b="0.1647" g="0.2157" r="0.4431" x="-4" y="6" z="-4" />
	</voxels>
	<skeleton />
	<skeletonVoxelBindings />
</model>